convert_videos/__init__.py
convert_videos/cli.py
convert_videos/colour.py
convert_videos/ffmpeg_converter.py
convert_videos/processor.py
convert_videos/settings.py
convert_videos/util.py
convert_videos/video_processor.py
convert_videos-2.10.0.dist-info/METADATA
convert_videos-2.10.0.dist-info/WHEEL
convert_videos-2.10.0.dist-info/entry_points.txt
convert_videos-2.10.0.dist-info/licenses/LICENSE.md
convert_videos-2.10.0.dist-info/RECORD
