Metadata-Version: 2.4
Name: convert_videos
Version: 2.10.0
Summary: This tool allows bulk conversion of videos using ffmpeg
Author-email: Justin Dray <justin@dray.be>
License-Expression: MIT
License-File: LICENSE.md
Requires-Python: <4,>=3.12.0
Requires-Dist: click<9,>=8.1.3
Requires-Dist: colorama<0.5,>=0.4.6
Requires-Dist: ffmpy<0.7,>=0.6.0
Requires-Dist: iso639<0.2,>=0.1.4
Requires-Dist: prettytable<4,>=3.7.0
Requires-Dist: stringcase<2,>=1.2.0
Requires-Dist: video-utils<3,>=2.4.7
